exampledatascienceproject/__init__.py
exampledatascienceproject-0.3.0.dist-info/WHEEL
exampledatascienceproject-0.3.0.dist-info/METADATA
exampledatascienceproject-0.3.0.dist-info/RECORD
