Metadata-Version: 2.1
Name: exampledatascienceproject
Version: 0.3.0
Summary: 
Author: Leonard Schuler
Author-email: leonard.schuler@example.com
Requires-Python: >=3.9,<4.0
Classifier: Programming Language :: Python :: 3
Classifier: Programming Language :: Python :: 3.10
Classifier: Programming Language :: Python :: 3.9
Requires-Dist: pendulum (>=2.1.2,<3.0.0)
